edc_microbiology/__init__.py
edc_microbiology/admin.py
edc_microbiology/admin_site.py
edc_microbiology/apps.py
edc_microbiology/auth_objects.py
edc_microbiology/auths.py
edc_microbiology/choices.py
edc_microbiology/constants.py
edc_microbiology/fieldsets.py
edc_microbiology/form_validators.py
edc_microbiology/forms.py
edc_microbiology/migrations/0001_initial.py
edc_microbiology/migrations/0002_auto_20220223_2236.py
edc_microbiology/migrations/0003_auto_20220223_2256.py
edc_microbiology/migrations/0004_auto_20220223_2258.py
edc_microbiology/migrations/0005_auto_20220224_1509.py
edc_microbiology/migrations/0006_auto_20220224_1826.py
edc_microbiology/migrations/0007_auto_20220224_1910.py
edc_microbiology/migrations/0008_auto_20220224_1926.py
edc_microbiology/migrations/0009_auto_20220711_1230.py
edc_microbiology/migrations/0010_alter_microbiology_options_and_more.py
edc_microbiology/migrations/0011_alter_microbiology_options_and_more.py
edc_microbiology/migrations/0012_alter_historicalmicrobiology_site_and_more.py
edc_microbiology/migrations/0013_alter_historicalmicrobiology_revision_and_more.py
edc_microbiology/migrations/0014_alter_historicalmicrobiology_device_modified_and_more.py
edc_microbiology/migrations/0015_alter_historicalmicrobiology_device_created_and_more.py
edc_microbiology/migrations/0016_alter_historicalmicrobiology_device_created_and_more.py
edc_microbiology/migrations/0017_alter_historicalmicrobiology_blood_culture_organism_text_and_more.py
edc_microbiology/migrations/__init__.py
edc_microbiology/model_mixins/__init__.py
edc_microbiology/model_mixins/blood_culture.py
edc_microbiology/model_mixins/csf_genexpert.py
edc_microbiology/model_mixins/histopathology.py
edc_microbiology/model_mixins/sputum_afb.py
edc_microbiology/model_mixins/sputum_culture.py
edc_microbiology/model_mixins/sputum_genexpert.py
edc_microbiology/model_mixins/urinary_lam.py
edc_microbiology/model_mixins/urine_culture.py
edc_microbiology/modeladmin_mixins/__init__.py
edc_microbiology-1.3.0.dist-info/licenses/LICENSE
edc_microbiology-1.3.0.dist-info/WHEEL
edc_microbiology-1.3.0.dist-info/METADATA
edc_microbiology-1.3.0.dist-info/RECORD
